odoo/addons/account_tax_repartition_line_tax_group_account/README.rst
odoo/addons/account_tax_repartition_line_tax_group_account/__init__.py
odoo/addons/account_tax_repartition_line_tax_group_account/__manifest__.py
odoo/addons/account_tax_repartition_line_tax_group_account/i18n/account_tax_repartition_line_tax_group_account.pot
odoo/addons/account_tax_repartition_line_tax_group_account/i18n/es.po
odoo/addons/account_tax_repartition_line_tax_group_account/i18n/it.po
odoo/addons/account_tax_repartition_line_tax_group_account/models/__init__.py
odoo/addons/account_tax_repartition_line_tax_group_account/models/account_tax_group.py
odoo/addons/account_tax_repartition_line_tax_group_account/models/account_tax_repartition_line.py
odoo/addons/account_tax_repartition_line_tax_group_account/readme/CONFIGURE.md
odoo/addons/account_tax_repartition_line_tax_group_account/readme/CONTRIBUTORS.md
odoo/addons/account_tax_repartition_line_tax_group_account/readme/DESCRIPTION.md
odoo/addons/account_tax_repartition_line_tax_group_account/readme/USAGE.md
odoo/addons/account_tax_repartition_line_tax_group_account/static/description/icon.png
odoo/addons/account_tax_repartition_line_tax_group_account/static/description/index.html
odoo/addons/account_tax_repartition_line_tax_group_account/tests/__init__.py
odoo/addons/account_tax_repartition_line_tax_group_account/tests/test_account_tax_repartition_line_tax_group_account.py
odoo/addons/account_tax_repartition_line_tax_group_account/views/account_tax_group_views.xml
odoo_addon_account_tax_repartition_line_tax_group_account-17.0.1.0.0.6.dist-info/METADATA
odoo_addon_account_tax_repartition_line_tax_group_account-17.0.1.0.0.6.dist-info/WHEEL
odoo_addon_account_tax_repartition_line_tax_group_account-17.0.1.0.0.6.dist-info/top_level.txt
odoo_addon_account_tax_repartition_line_tax_group_account-17.0.1.0.0.6.dist-info/RECORD
